CHANGES.rst
LICENSE
MANIFEST.in
README.rst
setup.cfg
setup.py
aiokafka/__init__.py
aiokafka/abc.py
aiokafka/client.py
aiokafka/cluster.py
aiokafka/conn.py
aiokafka/errors.py
aiokafka/helpers.py
aiokafka/structs.py
aiokafka/util.py
aiokafka/consumer/__init__.py
aiokafka/consumer/consumer.py
aiokafka/consumer/fetcher.py
aiokafka/consumer/group_coordinator.py
aiokafka/consumer/subscription_state.py
aiokafka/producer/__init__.py
aiokafka/producer/message_accumulator.py
aiokafka/producer/producer.py
aiokafka/producer/sender.py
aiokafka/producer/transaction_manager.py
aiokafka/protocol/coordination.py
aiokafka/protocol/fetch.py
aiokafka/protocol/produce.py
aiokafka/protocol/transaction.py
aiokafka/record/__init__.py
aiokafka/record/_crc32c.py
aiokafka/record/control_record.py
aiokafka/record/default_records.py
aiokafka/record/legacy_records.py
aiokafka/record/memory_records.py
aiokafka/record/util.py
aiokafka/record/_crecords/__init__.py
aiokafka/record/_crecords/consts.pxi
aiokafka/record/_crecords/crc32c.c
aiokafka/record/_crecords/crc32c.h
aiokafka/record/_crecords/cutil.c
aiokafka/record/_crecords/cutil.pxd
aiokafka/record/_crecords/cutil.pyx
aiokafka/record/_crecords/default_records.c
aiokafka/record/_crecords/default_records.pxd
aiokafka/record/_crecords/default_records.pyx
aiokafka/record/_crecords/hton.pxd
aiokafka/record/_crecords/legacy_records.c
aiokafka/record/_crecords/legacy_records.pxd
aiokafka/record/_crecords/legacy_records.pyx
aiokafka/record/_crecords/memory_records.c
aiokafka/record/_crecords/memory_records.pyx
beamm_aiokafka.egg-info/PKG-INFO
beamm_aiokafka.egg-info/SOURCES.txt
beamm_aiokafka.egg-info/dependency_links.txt
beamm_aiokafka.egg-info/requires.txt
beamm_aiokafka.egg-info/top_level.txt